DEPENDS.txt
LICENSE.txt
MANIFEST.in
setup.cfg
setup.py
./pvmpy/__init__.py
./pvmpy/base_pvm.py
./pvmpy/extended_pvm.py
./pvmpy/strel_pvm.py
pvmpy/__init__.py
pvmpy/base_pvm.py
pvmpy/extended_pvm.py
pvmpy/strel_pvm.py
pvmpy.egg-info/PKG-INFO
pvmpy.egg-info/SOURCES.txt
pvmpy.egg-info/dependency_links.txt
pvmpy.egg-info/not-zip-safe
pvmpy.egg-info/top_level.txt