Metadata-Version: 1.1
Name: pvmpy
Version: 1.1
Summary: Partial Volume Morphology
Home-page: https://github.com/JDWarner/pvmpy
Author: Joshua Warner
Author-email: joshua.dale.warner@gmail.com
License: Modified BSD
Download-URL: https://github.com/JDWarner/pvmpy
Platform: UNKNOWN
Classifier: Development Status :: 4 - Beta
Classifier: Environment :: Console
Classifier: Intended Audience :: Developers
Classifier: Intended Audience :: Science/Research
Classifier: License :: OSI Approved :: BSD License
Classifier: Programming Language :: Python
Classifier: Programming Language :: Python :: 3
Classifier: Topic :: Scientific/Engineering
Classifier: Operating System :: Microsoft :: Windows
Classifier: Operating System :: POSIX
Classifier: Operating System :: Unix
Classifier: Operating System :: MacOS
Requires: numpy (>= 1.6.0)
Requires: scipy (>= 0.9.0)
